mcp_openweather/__init__.py
mcp_openweather/__main__.py
mcp_openweather/server.py
mcp_openweather-1.0.0.dist-info/METADATA
mcp_openweather-1.0.0.dist-info/WHEEL
mcp_openweather-1.0.0.dist-info/entry_points.txt
mcp_openweather-1.0.0.dist-info/RECORD
