Metadata-Version: 2.4
Name: mcp-openweather
Version: 1.0.0
Summary: Weather Forecast MCP Server Powered by OpenWeatherMap
Requires-Python: >=3.10
Requires-Dist: mcp[cli]>=1.6.0
Requires-Dist: requests>=2.32.3
